airflow-stubs/__init__.pyi
airflow-stubs/configuration.pyi
airflow-stubs/exceptions.pyi
airflow-stubs/logging_config.pyi
airflow-stubs/plugins_manager.pyi
airflow-stubs/policies.pyi
airflow-stubs/providers_manager.pyi
airflow-stubs/sentry.pyi
airflow-stubs/settings.pyi
airflow-stubs/stats.pyi
airflow-stubs/templates.pyi
airflow-stubs/typing_compat.pyi
airflow-stubs/version.pyi
airflow-stubs/api/__init__.pyi
airflow-stubs/api/auth/__init__.pyi
airflow-stubs/api/auth/backend/__init__.pyi
airflow-stubs/api/auth/backend/basic_auth.pyi
airflow-stubs/api/auth/backend/default.pyi
airflow-stubs/api/auth/backend/deny_all.pyi
airflow-stubs/api/auth/backend/session.pyi
airflow-stubs/api/client/__init__.pyi
airflow-stubs/api/client/api_client.pyi
airflow-stubs/api/client/json_client.pyi
airflow-stubs/api/client/local_client.pyi
airflow-stubs/api/common/__init__.pyi
airflow-stubs/api/common/airflow_health.pyi
airflow-stubs/api/common/delete_dag.pyi
airflow-stubs/api/common/mark_tasks.pyi
airflow-stubs/api/common/trigger_dag.pyi
airflow-stubs/api/common/experimental/__init__.pyi
airflow-stubs/api/common/experimental/delete_dag.pyi
airflow-stubs/api/common/experimental/get_code.pyi
airflow-stubs/api/common/experimental/get_dag_run_state.pyi
airflow-stubs/api/common/experimental/get_dag_runs.pyi
airflow-stubs/api/common/experimental/get_lineage.pyi
airflow-stubs/api/common/experimental/get_task.pyi
airflow-stubs/api/common/experimental/get_task_instance.pyi
airflow-stubs/api/common/experimental/mark_tasks.pyi
airflow-stubs/api/common/experimental/pool.pyi
airflow-stubs/api/common/experimental/trigger_dag.pyi
airflow-stubs/api_connexion/__init__.pyi
airflow-stubs/api_connexion/exceptions.pyi
airflow-stubs/api_connexion/parameters.pyi
airflow-stubs/api_connexion/security.pyi
airflow-stubs/api_connexion/types.pyi
airflow-stubs/api_connexion/endpoints/__init__.pyi
airflow-stubs/api_connexion/endpoints/config_endpoint.pyi
airflow-stubs/api_connexion/endpoints/connection_endpoint.pyi
airflow_stubs-0.0.1.dist-info/METADATA
airflow_stubs-0.0.1.dist-info/WHEEL
airflow_stubs-0.0.1.dist-info/licenses/LICENSE.txt
airflow_stubs-0.0.1.dist-info/RECORD
