Metadata-Version: 2.3
Name: airflow-stubs
Version: 0.0.1
Summary: Type stubs for when Airflow is not installed
Project-URL: Documentation, https://github.com/maresb/airflow-stubs#readme
Project-URL: Issues, https://github.com/maresb/airflow-stubs/issues
Project-URL: Source, https://github.com/maresb/airflow-stubs
Author-email: Ben Mares <services-airflow-stubs@tensorial.com>
License-Expression: MIT
License-File: LICENSE.txt
Classifier: Development Status :: 4 - Beta
Classifier: Programming Language :: Python
Classifier: Programming Language :: Python :: 3.8
Classifier: Programming Language :: Python :: 3.9
Classifier: Programming Language :: Python :: 3.10
Classifier: Programming Language :: Python :: 3.11
Classifier: Programming Language :: Python :: 3.12
Classifier: Programming Language :: Python :: Implementation :: CPython
Classifier: Programming Language :: Python :: Implementation :: PyPy
Requires-Python: >=3.8
